sage_patchbot/__init__.py
sage_patchbot/cached_property.py
sage_patchbot/digest_transport.py
sage_patchbot/http_post_file.py
sage_patchbot/patchbot.py
sage_patchbot/plugins.py
sage_patchbot/serve.wsgi
sage_patchbot/trac.py
sage_patchbot/trac_error.py
sage_patchbot/trac_ticket.py
sage_patchbot/update_version.py
sage_patchbot/util.py
sage_patchbot/server/__init__.py
sage_patchbot/server/__main__.py
sage_patchbot/server/db.py
sage_patchbot/server/serve.py
sage_patchbot/server/tools.py
sage_patchbot/server/images/favicon.png
sage_patchbot/server/images/icon-ApplyFailed.png
sage_patchbot/server/images/icon-ApplyFailed.svg
sage_patchbot/server/images/icon-BuildFailed.png
sage_patchbot/server/images/icon-BuildFailed.svg
sage_patchbot/server/images/icon-Empty.png
sage_patchbot/server/images/icon-Empty.svg
sage_patchbot/server/images/icon-New.png
sage_patchbot/server/images/icon-New.svg
sage_patchbot/server/images/icon-NoPatch.png
sage_patchbot/server/images/icon-NoPatch.svg
sage_patchbot/server/images/icon-Pending.png
sage_patchbot/server/images/icon-Pending.svg
sage_patchbot/server/images/icon-PluginFailed.png
sage_patchbot/server/images/icon-PluginFailed.svg
sage_patchbot/server/images/icon-PluginOnly.png
sage_patchbot/server/images/icon-PluginOnly.svg
sage_patchbot/server/images/icon-PluginOnlyFailed.png
sage_patchbot/server/images/icon-PluginOnlyFailed.svg
sage_patchbot/server/images/icon-SmallPluginFailed.svg
sage_patchbot/server/images/icon-SmallPluginPassed.svg
sage_patchbot/server/images/icon-Spkg.png
sage_patchbot/server/images/icon-Spkg.svg
sage_patchbot/server/images/icon-TestsFailed.png
sage_patchbot/server/images/icon-TestsFailed.svg
sage_patchbot/server/images/icon-TestsPassed.png
sage_patchbot/server/images/icon-TestsPassed.svg
sage_patchbot/server/images/icon-TestsPassedOnRetry.png
sage_patchbot/server/images/icon-TestsPassedOnRetry.svg
sage_patchbot/server/static/default.css
sage_patchbot/server/templates/banner.html
sage_patchbot-3.0.2.dist-info/LICENSE
sage_patchbot-3.0.2.dist-info/METADATA
sage_patchbot-3.0.2.dist-info/WHEEL
sage_patchbot-3.0.2.dist-info/entry_points.txt
sage_patchbot-3.0.2.dist-info/top_level.txt
sage_patchbot-3.0.2.dist-info/RECORD
