Metadata-Version: 2.1
Name: sage-patchbot
Version: 3.0.2
Summary: bot for automatic test of sagemath trac tickets
Home-page: https://github.com/sagemath/sage-patchbot
Author: SageMath Developers
License: GPL
Keywords: sagemath
Platform: UNKNOWN
Classifier: Programming Language :: Python :: 3
Classifier: License :: OSI Approved :: GNU General Public License v2 or later (GPLv2+)
Classifier: Operating System :: OS Independent
Classifier: Topic :: Scientific/Engineering :: Mathematics
Classifier: Topic :: Software Development :: Quality Assurance
Requires-Python: >=3.7
License-File: LICENSE
Requires-Dist: pyflakes
Requires-Dist: pycodestyle
